setup.py
akatsuki/__init__.py
akatsuki/bib2html.py
akatsuki/bib2wp.py
akatsuki/exporter.py
akatsuki/parser.py
akatsuki/utils.py
akatsuki.egg-info/PKG-INFO
akatsuki.egg-info/SOURCES.txt
akatsuki.egg-info/dependency_links.txt
akatsuki.egg-info/requires.txt
akatsuki.egg-info/top_level.txt
scripts/bib2html
scripts/bib2wp